basemodels/__init__.py
basemodels/constants.py
basemodels/via.py
basemodels/manifest/__init__.py
basemodels/manifest/manifest.py
basemodels/manifest/restricted_audience.py
basemodels/manifest/data/__init__.py
basemodels/manifest/data/groundtruth.py
basemodels/manifest/data/preprocess.py
basemodels/manifest/data/taskdata.py
test/__init__.py
test/test_manifest.py
test/test_preprocess.py
human_protocol_basemodels-1.1.5.dist-info/METADATA
human_protocol_basemodels-1.1.5.dist-info/WHEEL
human_protocol_basemodels-1.1.5.dist-info/top_level.txt
human_protocol_basemodels-1.1.5.dist-info/zip-safe
human_protocol_basemodels-1.1.5.dist-info/RECORD
