Metadata-Version: 2.1
Name: human-protocol-basemodels
Version: 1.1.5
Summary: Common data models shared by various components of the Human Protocol stack
Home-page: https://github.com/humanprotocol/human-protocol/packages/sdk/python/human-protocol-basemodels
Author: HUMAN Protocol
Classifier: Intended Audience :: Developers
Classifier: Operating System :: OS Independent
Classifier: Programming Language :: Python
Requires-Dist: requests (>=2)
Requires-Dist: typing-extensions
Requires-Dist: pydantic (>=1.6)
